geoffrey_pytest-0.0.2.dist-info/DESCRIPTION.rst
geoffrey_pytest-0.0.2.dist-info/RECORD
geoffrey_pytest-0.0.2.dist-info/WHEEL
geoffrey_pytest-0.0.2.dist-info/top_level.txt
geoffrey_pytest-0.0.2.dist-info/metadata.json
geoffrey_pytest-0.0.2.dist-info/METADATA
geoffreyplugins/pytest.py
geoffreyplugins/__init__.py
geoffreyplugins/pytest/main.js
geoffreyplugins/pytest/assets/.gitkeep
geoffreyplugins/pytest/assets/wip-widget.html
geoffreyplugins/pytest/assets/wip-widget.css
