Metadata-Version: 2.0
Name: geoffrey-pytest
Version: 0.0.2
Summary: Geoffrey pytest plugin runner.
Home-page: https://github.com/nilp0inter/geoffrey-pytest
Author: Roberto Abdelkader Martínez Pérez
Author-email: robertomartinezp@gmail.com
License: UNKNOWN
Platform: UNKNOWN
